microperf/__init__.py
microperf/__main__.py
microperf/_perf-script.py
microperf/commands.py
microperf/queries.py
microperf-1.0.1.dist-info/METADATA
microperf-1.0.1.dist-info/WHEEL
microperf-1.0.1.dist-info/entry_points.txt
microperf-1.0.1.dist-info/licenses/LICENSE
microperf-1.0.1.dist-info/RECORD
