Metadata-Version: 2.4
Name: microperf
Version: 1.0.1
Summary: A small tool using perf to provide more performance insights.
Project-URL: Homepage, https://github.com/nicovank/microperf
Project-URL: Bug Tracker, https://github.com/nicovank/microperf/issues
Author-email: Nicolas van Kempen <nvankemp@gmail.com>
License-File: LICENSE
Classifier: License :: OSI Approved :: Apache Software License
Classifier: Operating System :: POSIX :: Linux
Classifier: Programming Language :: Python :: 3
Requires-Python: >=3.9
Requires-Dist: docker==7.1.0
Requires-Dist: presto-python-client==0.8.4
Requires-Dist: rich==13.9.4
